<?xml version="1.0" encoding="UTF-8"?>

<FLOW VERSION="3.0" CLEANUP="true">
  <COMMENT></COMMENT>

  <!-- nodes -->

<BRANCH TIMEOUT="" SWITCH="/complianceProgram/id">
  <COMMENT></COMMENT>

  <!-- nodes -->

<INVOKE NAME="/[^ ]/" TIMEOUT="" SERVICE="ADESPCompliance.adapters.complianceProgram:updateComplianceProgram" VALIDATE-IN="$none" VALIDATE-OUT="$none">
  <COMMENT></COMMENT>

  <!-- nodes -->

<MAP MODE="INPUT">
  <MAPTARGET>

<Values version="2.0">
  <record name="xml" javaclass="com.wm.util.Values">
    <value name="node_type">record</value>
    <value name="node_subtype">unknown</value>
    <value name="is_public">false</value>
    <value name="field_name">updateComplianceProgramInput</value>
    <value name="field_type">record</value>
    <value name="field_dim">0</value>
    <value name="nillable">true</value>
    <value name="form_qualified">false</value>
    <value name="is_global">false</value>
    <array name="rec_fields" type="record" depth="1">
      <record javaclass="com.wm.util.Values">
        <value name="node_type">record</value>
        <value name="node_subtype">unknown</value>
        <value name="is_public">false</value>
        <value name="field_name">updateComplianceProgramInput</value>
        <value name="field_type">record</value>
        <value name="field_dim">0</value>
        <value name="nillable">true</value>
        <value name="form_qualified">false</value>
        <value name="is_global">false</value>
        <array name="rec_fields" type="record" depth="1">
          <record javaclass="com.wm.util.Values">
            <value name="node_type">record</value>
            <value name="node_subtype">unknown</value>
            <value name="is_public">false</value>
            <value name="field_name">overrideCredentials</value>
            <value name="field_type">record</value>
            <value name="field_dim">0</value>
            <value name="nillable">true</value>
            <value name="form_qualified">false</value>
            <value name="is_global">false</value>
            <array name="rec_fields" type="record" depth="1">
            </array>
            <value name="modifiable">true</value>
          </record>
          <record javaclass="com.wm.util.Values">
            <value name="node_type">unknown</value>
            <value name="node_subtype">unknown</value>
            <value name="is_public">false</value>
            <value name="field_name">PROGRAMME_NAME</value>
            <value name="field_type">string</value>
            <value name="field_dim">0</value>
            <value name="nillable">true</value>
            <value name="form_qualified">false</value>
            <value name="is_global">false</value>
          </record>
          <record javaclass="com.wm.util.Values">
            <value name="node_type">unknown</value>
            <value name="node_subtype">unknown</value>
            <value name="is_public">false</value>
            <value name="field_name">MODIFIED_BY</value>
            <value name="field_type">string</value>
            <value name="field_dim">0</value>
            <value name="nillable">true</value>
            <value name="form_qualified">false</value>
            <value name="is_global">false</value>
          </record>
          <record javaclass="com.wm.util.Values">
            <value name="node_type">unknown</value>
            <value name="node_subtype">unknown</value>
            <value name="is_public">false</value>
            <value name="field_name">STATUS</value>
            <value name="field_type">string</value>
            <value name="field_dim">0</value>
            <value name="nillable">true</value>
            <value name="form_qualified">false</value>
            <value name="is_global">false</value>
          </record>
          <record javaclass="com.wm.util.Values">
            <value name="node_type">unknown</value>
            <value name="node_subtype">unknown</value>
            <value name="is_public">false</value>
            <value name="field_name">ISACTIVE</value>
            <value name="field_type">string</value>
            <value name="field_dim">0</value>
            <value name="nillable">true</value>
            <value name="form_qualified">false</value>
            <value name="is_global">false</value>
          </record>
          <record javaclass="com.wm.util.Values">
            <value name="node_type">unknown</value>
            <value name="node_subtype">unknown</value>
            <value name="is_public">false</value>
            <value name="field_name">YEAR</value>
            <value name="field_type">string</value>
            <value name="field_dim">0</value>
            <value name="nillable">true</value>
            <value name="form_qualified">false</value>
            <value name="is_global">false</value>
          </record>
          <record javaclass="com.wm.util.Values">
            <value name="node_type">unknown</value>
            <value name="node_subtype">unknown</value>
            <value name="is_public">false</value>
            <value name="field_name">ID</value>
            <value name="field_type">string</value>
            <value name="field_dim">0</value>
            <value name="nillable">true</value>
            <value name="form_qualified">false</value>
            <value name="is_global">false</value>
          </record>
        </array>
        <value name="modifiable">true</value>
      </record>
      <record javaclass="com.wm.util.Values">
        <value name="node_type">record</value>
        <value name="node_subtype">unknown</value>
        <value name="is_public">false</value>
        <value name="field_name">$connectionName</value>
        <value name="field_type">string</value>
        <value name="field_dim">0</value>
        <value name="field_opt">true</value>
        <value name="nillable">false</value>
        <value name="form_qualified">false</value>
        <value name="is_global">false</value>
      </record>
    </array>
    <value name="modifiable">true</value>
  </record>
</Values>
</MAPTARGET>
  <MAPSOURCE>

<Values version="2.0">
  <record name="xml" javaclass="com.wm.util.Values">
    <value name="node_type">record</value>
    <value name="node_subtype">unknown</value>
    <value name="is_public">false</value>
    <value name="field_type">record</value>
    <value name="field_dim">0</value>
    <value name="nillable">true</value>
    <value name="form_qualified">false</value>
    <value name="is_global">false</value>
    <array name="rec_fields" type="record" depth="1">
      <record javaclass="com.wm.util.Values">
        <value name="node_type">record</value>
        <value name="node_subtype">unknown</value>
        <value name="node_comment"></value>
        <record name="node_hints" javaclass="com.wm.util.Values">
          <value name="field_largerEditor">false</value>
          <value name="field_password">false</value>
        </record>
        <value name="is_public">false</value>
        <value name="field_name">complianceProgram</value>
        <value name="field_type">recref</value>
        <value name="field_dim">0</value>
        <value name="wrapper_type">IData</value>
        <value name="nillable">true</value>
        <value name="form_qualified">false</value>
        <value name="is_global">false</value>
        <value name="rec_closed">true</value>
        <value name="modifiable">true</value>
        <value name="rec_ref">ADESPCompliance.documents:ComplianceProgram</value>
      </record>
      <record javaclass="com.wm.util.Values">
        <value name="node_type">record</value>
        <value name="node_subtype">unknown</value>
        <value name="node_comment"></value>
        <record name="node_hints" javaclass="com.wm.util.Values">
          <value name="field_largerEditor">false</value>
          <value name="field_password">false</value>
        </record>
        <value name="is_public">false</value>
        <value name="field_name">logUserInfo</value>
        <value name="field_type">recref</value>
        <value name="field_dim">0</value>
        <value name="wrapper_type">IData</value>
        <value name="nillable">true</value>
        <value name="form_qualified">false</value>
        <value name="is_global">false</value>
        <value name="rec_closed">true</value>
        <value name="modifiable">true</value>
        <value name="rec_ref">IXLoggingServer.documents:LogUserInformation</value>
      </record>
    </array>
    <value name="modifiable">true</value>
  </record>
</Values>
</MAPSOURCE>

  <!-- nodes -->

<MAPCOPY FROM="/complianceProgram;4;0;ADESPCompliance.documents:ComplianceProgram/status;1;0" TO="/updateComplianceProgramInput;2;0/STATUS;1;0">
</MAPCOPY>

<MAPCOPY FROM="/complianceProgram;4;0;ADESPCompliance.documents:ComplianceProgram/year;1;0" TO="/updateComplianceProgramInput;2;0/YEAR;1;0">
</MAPCOPY>

<MAPCOPY FROM="/complianceProgram;4;0;ADESPCompliance.documents:ComplianceProgram/id;1;0" TO="/updateComplianceProgramInput;2;0/ID;1;0">
</MAPCOPY>

<MAPCOPY FROM="/logUserInfo;4;0;IXLoggingServer.documents:LogUserInformation/userId;1;0" TO="/updateComplianceProgramInput;2;0/MODIFIED_BY;1;0">
</MAPCOPY>

<MAPSET NAME="Setter" OVERWRITE="true" VARIABLES="false" GLOBALVARIABLES="false" FIELD="/updateComplianceProgramInput;2;0/ISACTIVE;1;0">
  <DATA ENCODING="XMLValues" I18N="true">

<Values version="2.0">
  <value name="xml">true</value>
  <record name="type" javaclass="com.wm.util.Values">
    <value name="node_type">unknown</value>
    <value name="node_subtype">unknown</value>
    <value name="is_public">false</value>
    <value name="field_name">ISACTIVE</value>
    <value name="field_type">string</value>
    <value name="field_dim">0</value>
    <value name="nillable">true</value>
    <value name="form_qualified">false</value>
    <value name="is_global">false</value>
  </record>
</Values>
</DATA>
</MAPSET>

<MAPCOPY FROM="/complianceProgram;4;0;ADESPCompliance.documents:ComplianceProgram/programName;1;0" TO="/updateComplianceProgramInput;2;0/PROGRAMME_NAME;1;0">
</MAPCOPY>
</MAP>

<MAP MODE="OUTPUT">
  <MAPTARGET>

<Values version="2.0">
  <record name="xml" javaclass="com.wm.util.Values">
    <value name="node_type">record</value>
    <value name="node_subtype">unknown</value>
    <value name="is_public">false</value>
    <value name="field_type">record</value>
    <value name="field_dim">0</value>
    <value name="nillable">true</value>
    <value name="form_qualified">false</value>
    <value name="is_global">false</value>
    <array name="rec_fields" type="record" depth="1">
      <record javaclass="com.wm.util.Values">
        <value name="node_type">record</value>
        <value name="node_subtype">unknown</value>
        <value name="is_public">false</value>
        <value name="field_name">updateComplianceProgramInput</value>
        <value name="field_type">record</value>
        <value name="field_dim">0</value>
        <value name="nillable">true</value>
        <value name="form_qualified">false</value>
        <value name="is_global">false</value>
        <array name="rec_fields" type="record" depth="1">
          <record javaclass="com.wm.util.Values">
            <value name="node_type">unknown</value>
            <value name="node_subtype">unknown</value>
            <value name="is_public">false</value>
            <value name="field_name">PROGRAMME_NAME</value>
            <value name="field_type">string</value>
            <value name="field_dim">0</value>
            <value name="nillable">true</value>
            <value name="form_qualified">false</value>
            <value name="is_global">false</value>
          </record>
          <record javaclass="com.wm.util.Values">
            <value name="node_type">unknown</value>
            <value name="node_subtype">unknown</value>
            <value name="is_public">false</value>
            <value name="field_name">MODIFIED_BY</value>
            <value name="field_type">string</value>
            <value name="field_dim">0</value>
            <value name="nillable">true</value>
            <value name="form_qualified">false</value>
            <value name="is_global">false</value>
          </record>
          <record javaclass="com.wm.util.Values">
            <value name="node_type">unknown</value>
            <value name="node_subtype">unknown</value>
            <value name="is_public">false</value>
            <value name="field_name">STATUS</value>
            <value name="field_type">string</value>
            <value name="field_dim">0</value>
            <value name="nillable">true</value>
            <value name="form_qualified">false</value>
            <value name="is_global">false</value>
          </record>
          <record javaclass="com.wm.util.Values">
            <value name="node_type">unknown</value>
            <value name="node_subtype">unknown</value>
            <value name="is_public">false</value>
            <value name="field_name">ISACTIVE</value>
            <value name="field_type">string</value>
            <value name="field_dim">0</value>
            <value name="nillable">true</value>
            <value name="form_qualified">false</value>
            <value name="is_global">false</value>
          </record>
          <record javaclass="com.wm.util.Values">
            <value name="node_type">unknown</value>
            <value name="node_subtype">unknown</value>
            <value name="is_public">false</value>
            <value name="field_name">YEAR</value>
            <value name="field_type">string</value>
            <value name="field_dim">0</value>
            <value name="nillable">true</value>
            <value name="form_qualified">false</value>
            <value name="is_global">false</value>
          </record>
          <record javaclass="com.wm.util.Values">
            <value name="node_type">unknown</value>
            <value name="node_subtype">unknown</value>
            <value name="is_public">false</value>
            <value name="field_name">ID</value>
            <value name="field_type">string</value>
            <value name="field_dim">0</value>
            <value name="nillable">true</value>
            <value name="form_qualified">false</value>
            <value name="is_global">false</value>
          </record>
        </array>
        <value name="modifiable">true</value>
      </record>
      <record javaclass="com.wm.util.Values">
        <value name="node_type">record</value>
        <value name="node_subtype">unknown</value>
        <value name="node_comment"></value>
        <record name="node_hints" javaclass="com.wm.util.Values">
          <value name="field_largerEditor">false</value>
          <value name="field_password">false</value>
        </record>
        <value name="is_public">false</value>
        <value name="field_name">complianceProgram</value>
        <value name="field_type">recref</value>
        <value name="field_dim">0</value>
        <value name="wrapper_type">IData</value>
        <value name="nillable">true</value>
        <value name="form_qualified">false</value>
        <value name="is_global">false</value>
        <value name="rec_closed">true</value>
        <value name="modifiable">true</value>
        <value name="rec_ref">ADESPCompliance.documents:ComplianceProgram</value>
      </record>
      <record javaclass="com.wm.util.Values">
        <value name="node_type">record</value>
        <value name="node_subtype">unknown</value>
        <value name="node_comment"></value>
        <record name="node_hints" javaclass="com.wm.util.Values">
          <value name="field_largerEditor">false</value>
          <value name="field_password">false</value>
        </record>
        <value name="is_public">false</value>
        <value name="field_name">logUserInfo</value>
        <value name="field_type">recref</value>
        <value name="field_dim">0</value>
        <value name="wrapper_type">IData</value>
        <value name="nillable">true</value>
        <value name="form_qualified">false</value>
        <value name="is_global">false</value>
        <value name="rec_closed">true</value>
        <value name="modifiable">true</value>
        <value name="rec_ref">IXLoggingServer.documents:LogUserInformation</value>
      </record>
      <record javaclass="com.wm.util.Values">
        <value name="node_type">record</value>
        <value name="node_subtype">unknown</value>
        <value name="is_public">false</value>
        <value name="field_name">updateComplianceProgramOutput</value>
        <value name="field_type">record</value>
        <value name="field_dim">0</value>
        <value name="nillable">true</value>
        <value name="form_qualified">false</value>
        <value name="is_global">false</value>
        <array name="rec_fields" type="record" depth="1">
        </array>
        <value name="modifiable">true</value>
      </record>
    </array>
    <value name="modifiable">true</value>
  </record>
</Values>
</MAPTARGET>
  <MAPSOURCE>

<Values version="2.0">
  <record name="xml" javaclass="com.wm.util.Values">
    <value name="node_type">record</value>
    <value name="node_subtype">unknown</value>
    <value name="is_public">false</value>
    <value name="field_name">updateComplianceProgramOutput</value>
    <value name="field_type">record</value>
    <value name="field_dim">0</value>
    <value name="nillable">true</value>
    <value name="form_qualified">false</value>
    <value name="is_global">false</value>
    <array name="rec_fields" type="record" depth="1">
      <record javaclass="com.wm.util.Values">
        <value name="node_type">record</value>
        <value name="node_subtype">unknown</value>
        <value name="is_public">false</value>
        <value name="field_name">updateComplianceProgramOutput</value>
        <value name="field_type">record</value>
        <value name="field_dim">0</value>
        <value name="nillable">true</value>
        <value name="form_qualified">false</value>
        <value name="is_global">false</value>
        <array name="rec_fields" type="record" depth="1">
        </array>
        <value name="modifiable">true</value>
      </record>
    </array>
    <value name="modifiable">true</value>
  </record>
</Values>
</MAPSOURCE>

  <!-- nodes -->

<MAPDELETE FIELD="/updateComplianceProgramInput;2;0">
</MAPDELETE>

<MAPDELETE FIELD="/updateComplianceProgramOutput;2;0">
</MAPDELETE>
</MAP>
</INVOKE>

<SEQUENCE NAME="$default" TIMEOUT="" EXIT-ON="FAILURE">
  <COMMENT></COMMENT>

  <!-- nodes -->

<INVOKE TIMEOUT="" SERVICE="IXCommon.maps:getSeqId" VALIDATE-IN="$none" VALIDATE-OUT="$none">
  <COMMENT>==</COMMENT>

  <!-- nodes -->

<MAP MODE="INPUT">
  <MAPTARGET>

<Values version="2.0">
  <record name="xml" javaclass="com.wm.util.Values">
    <value name="node_type">record</value>
    <value name="node_subtype">unknown</value>
    <value name="is_public">false</value>
    <value name="field_type">record</value>
    <value name="field_dim">0</value>
    <value name="wrapper_type">IData</value>
    <value name="nillable">true</value>
    <value name="form_qualified">false</value>
    <value name="is_global">false</value>
    <array name="rec_fields" type="record" depth="1">
      <record javaclass="com.wm.util.Values">
        <value name="node_type">record</value>
        <value name="node_subtype">unknown</value>
        <value name="node_comment"></value>
        <record name="node_hints" javaclass="com.wm.util.Values">
          <value name="field_usereditable">true</value>
          <value name="field_largerEditor">false</value>
          <value name="field_password">false</value>
        </record>
        <value name="is_public">false</value>
        <value name="field_name">seqName</value>
        <value name="field_type">string</value>
        <value name="field_dim">0</value>
        <array name="field_options" type="value" depth="1">
        </array>
        <value name="nillable">true</value>
        <value name="form_qualified">false</value>
        <value name="is_global">false</value>
      </record>
    </array>
    <value name="modifiable">true</value>
  </record>
</Values>
</MAPTARGET>
  <MAPSOURCE>

<Values version="2.0">
  <record name="xml" javaclass="com.wm.util.Values">
    <value name="node_type">record</value>
    <value name="node_subtype">unknown</value>
    <value name="is_public">false</value>
    <value name="field_type">record</value>
    <value name="field_dim">0</value>
    <value name="nillable">true</value>
    <value name="form_qualified">false</value>
    <value name="is_global">false</value>
    <array name="rec_fields" type="record" depth="1">
    </array>
    <value name="modifiable">true</value>
  </record>
</Values>
</MAPSOURCE>

  <!-- nodes -->

<MAPSET NAME="Setter" OVERWRITE="true" VARIABLES="false" GLOBALVARIABLES="false" FIELD="/seqName;1;0">
  <DATA ENCODING="XMLValues" I18N="true">

<Values version="2.0">
  <value name="xml">COMPLIANCE_PROGRAMME_SEQ</value>
  <record name="type" javaclass="com.wm.util.Values">
    <value name="node_type">record</value>
    <value name="node_subtype">unknown</value>
    <value name="node_comment"></value>
    <record name="node_hints" javaclass="com.wm.util.Values">
      <value name="field_usereditable">true</value>
      <value name="field_largerEditor">false</value>
      <value name="field_password">false</value>
    </record>
    <value name="is_public">false</value>
    <value name="field_name">seqName</value>
    <value name="field_type">string</value>
    <value name="field_dim">0</value>
    <array name="field_options" type="value" depth="1">
    </array>
    <value name="nillable">true</value>
    <value name="form_qualified">false</value>
    <value name="is_global">false</value>
  </record>
</Values>
</DATA>
</MAPSET>
</MAP>

<MAP MODE="OUTPUT">
  <MAPTARGET>

<Values version="2.0">
  <record name="xml" javaclass="com.wm.util.Values">
    <value name="node_type">record</value>
    <value name="node_subtype">unknown</value>
    <value name="is_public">false</value>
    <value name="field_type">record</value>
    <value name="field_dim">0</value>
    <value name="nillable">true</value>
    <value name="form_qualified">false</value>
    <value name="is_global">false</value>
    <array name="rec_fields" type="record" depth="1">
      <record javaclass="com.wm.util.Values">
        <value name="node_type">unknown</value>
        <value name="node_subtype">unknown</value>
        <value name="is_public">false</value>
        <value name="field_name">seqName</value>
        <value name="field_type">string</value>
        <value name="field_dim">0</value>
        <value name="nillable">true</value>
        <value name="form_qualified">false</value>
        <value name="is_global">false</value>
      </record>
      <record javaclass="com.wm.util.Values">
        <value name="node_type">record</value>
        <value name="node_subtype">unknown</value>
        <value name="node_comment"></value>
        <record name="node_hints" javaclass="com.wm.util.Values">
          <value name="field_largerEditor">false</value>
          <value name="field_password">false</value>
        </record>
        <value name="is_public">false</value>
        <value name="field_name">complianceProgram</value>
        <value name="field_type">recref</value>
        <value name="field_dim">0</value>
        <value name="wrapper_type">IData</value>
        <value name="nillable">true</value>
        <value name="form_qualified">false</value>
        <value name="is_global">false</value>
        <value name="rec_closed">true</value>
        <value name="modifiable">true</value>
        <value name="rec_ref">ADESPCompliance.documents:ComplianceProgram</value>
      </record>
      <record javaclass="com.wm.util.Values">
        <value name="node_type">record</value>
        <value name="node_subtype">unknown</value>
        <value name="node_comment"></value>
        <record name="node_hints" javaclass="com.wm.util.Values">
          <value name="field_largerEditor">false</value>
          <value name="field_password">false</value>
        </record>
        <value name="is_public">false</value>
        <value name="field_name">logUserInfo</value>
        <value name="field_type">recref</value>
        <value name="field_dim">0</value>
        <value name="wrapper_type">IData</value>
        <value name="nillable">true</value>
        <value name="form_qualified">false</value>
        <value name="is_global">false</value>
        <value name="rec_closed">true</value>
        <value name="modifiable">true</value>
        <value name="rec_ref">IXLoggingServer.documents:LogUserInformation</value>
      </record>
      <record javaclass="com.wm.util.Values">
        <value name="node_type">record</value>
        <value name="node_subtype">unknown</value>
        <value name="node_comment"></value>
        <record name="node_hints" javaclass="com.wm.util.Values">
          <value name="field_usereditable">true</value>
          <value name="field_largerEditor">false</value>
          <value name="field_password">false</value>
        </record>
        <value name="is_public">false</value>
        <value name="field_name">seqId</value>
        <value name="field_type">string</value>
        <value name="field_dim">0</value>
        <array name="field_options" type="value" depth="1">
        </array>
        <value name="nillable">true</value>
        <value name="form_qualified">false</value>
        <value name="is_global">false</value>
      </record>
    </array>
    <value name="modifiable">true</value>
  </record>
</Values>
</MAPTARGET>
  <MAPSOURCE>

<Values version="2.0">
  <record name="xml" javaclass="com.wm.util.Values">
    <value name="node_type">record</value>
    <value name="node_subtype">unknown</value>
    <value name="is_public">false</value>
    <value name="field_type">record</value>
    <value name="field_dim">0</value>
    <value name="wrapper_type">IData</value>
    <value name="nillable">true</value>
    <value name="form_qualified">false</value>
    <value name="is_global">false</value>
    <array name="rec_fields" type="record" depth="1">
      <record javaclass="com.wm.util.Values">
        <value name="node_type">record</value>
        <value name="node_subtype">unknown</value>
        <value name="node_comment"></value>
        <record name="node_hints" javaclass="com.wm.util.Values">
          <value name="field_usereditable">true</value>
          <value name="field_largerEditor">false</value>
          <value name="field_password">false</value>
        </record>
        <value name="is_public">false</value>
        <value name="field_name">seqId</value>
        <value name="field_type">string</value>
        <value name="field_dim">0</value>
        <array name="field_options" type="value" depth="1">
        </array>
        <value name="nillable">true</value>
        <value name="form_qualified">false</value>
        <value name="is_global">false</value>
      </record>
    </array>
    <value name="modifiable">true</value>
  </record>
</Values>
</MAPSOURCE>

  <!-- nodes -->

<MAPDELETE FIELD="/seqId;1;0">
</MAPDELETE>

<MAPDELETE FIELD="/seqName;1;0">
</MAPDELETE>

<MAPCOPY FROM="/seqId;1;0" TO="/complianceProgram;4;0;ADESPCompliance.documents:ComplianceProgram/id;1;0">
</MAPCOPY>
</MAP>
</INVOKE>

<INVOKE TIMEOUT="" SERVICE="ADESPCompliance.adapters.complianceProgram:insertComplianceProgram" VALIDATE-IN="$none" VALIDATE-OUT="$none">
  <COMMENT></COMMENT>

  <!-- nodes -->

<MAP MODE="INPUT">
  <MAPTARGET>

<Values version="2.0">
  <record name="xml" javaclass="com.wm.util.Values">
    <value name="node_type">record</value>
    <value name="node_subtype">unknown</value>
    <value name="is_public">false</value>
    <value name="field_name">insertComplianceProgramInput</value>
    <value name="field_type">record</value>
    <value name="field_dim">0</value>
    <value name="nillable">true</value>
    <value name="form_qualified">false</value>
    <value name="is_global">false</value>
    <array name="rec_fields" type="record" depth="1">
      <record javaclass="com.wm.util.Values">
        <value name="node_type">record</value>
        <value name="node_subtype">unknown</value>
        <value name="is_public">false</value>
        <value name="field_name">insertComplianceProgramInput</value>
        <value name="field_type">record</value>
        <value name="field_dim">0</value>
        <value name="nillable">true</value>
        <value name="form_qualified">false</value>
        <value name="is_global">false</value>
        <array name="rec_fields" type="record" depth="1">
          <record javaclass="com.wm.util.Values">
            <value name="node_type">record</value>
            <value name="node_subtype">unknown</value>
            <value name="is_public">false</value>
            <value name="field_name">overrideCredentials</value>
            <value name="field_type">record</value>
            <value name="field_dim">0</value>
            <value name="nillable">true</value>
            <value name="form_qualified">false</value>
            <value name="is_global">false</value>
            <array name="rec_fields" type="record" depth="1">
            </array>
            <value name="modifiable">true</value>
          </record>
          <record javaclass="com.wm.util.Values">
            <value name="node_type">unknown</value>
            <value name="node_subtype">unknown</value>
            <value name="is_public">false</value>
            <value name="field_name">ID</value>
            <value name="field_type">string</value>
            <value name="field_dim">0</value>
            <value name="nillable">true</value>
            <value name="form_qualified">false</value>
            <value name="is_global">false</value>
          </record>
          <record javaclass="com.wm.util.Values">
            <value name="node_type">unknown</value>
            <value name="node_subtype">unknown</value>
            <value name="is_public">false</value>
            <value name="field_name">PROGRAMME_NAME</value>
            <value name="field_type">string</value>
            <value name="field_dim">0</value>
            <value name="nillable">true</value>
            <value name="form_qualified">false</value>
            <value name="is_global">false</value>
          </record>
          <record javaclass="com.wm.util.Values">
            <value name="node_type">unknown</value>
            <value name="node_subtype">unknown</value>
            <value name="is_public">false</value>
            <value name="field_name">MODIFIED_BY</value>
            <value name="field_type">string</value>
            <value name="field_dim">0</value>
            <value name="nillable">true</value>
            <value name="form_qualified">false</value>
            <value name="is_global">false</value>
          </record>
          <record javaclass="com.wm.util.Values">
            <value name="node_type">unknown</value>
            <value name="node_subtype">unknown</value>
            <value name="is_public">false</value>
            <value name="field_name">STATUS</value>
            <value name="field_type">string</value>
            <value name="field_dim">0</value>
            <value name="nillable">true</value>
            <value name="form_qualified">false</value>
            <value name="is_global">false</value>
          </record>
          <record javaclass="com.wm.util.Values">
            <value name="node_type">unknown</value>
            <value name="node_subtype">unknown</value>
            <value name="is_public">false</value>
            <value name="field_name">ISACTIVE</value>
            <value name="field_type">string</value>
            <value name="field_dim">0</value>
            <value name="nillable">true</value>
            <value name="form_qualified">false</value>
            <value name="is_global">false</value>
          </record>
          <record javaclass="com.wm.util.Values">
            <value name="node_type">unknown</value>
            <value name="node_subtype">unknown</value>
            <value name="is_public">false</value>
            <value name="field_name">YEAR</value>
            <value name="field_type">string</value>
            <value name="field_dim">0</value>
            <value name="nillable">true</value>
            <value name="form_qualified">false</value>
            <value name="is_global">false</value>
          </record>
        </array>
        <value name="modifiable">true</value>
      </record>
      <record javaclass="com.wm.util.Values">
        <value name="node_type">record</value>
        <value name="node_subtype">unknown</value>
        <value name="is_public">false</value>
        <value name="field_name">$connectionName</value>
        <value name="field_type">string</value>
        <value name="field_dim">0</value>
        <value name="field_opt">true</value>
        <value name="nillable">false</value>
        <value name="form_qualified">false</value>
        <value name="is_global">false</value>
      </record>
    </array>
    <value name="modifiable">true</value>
  </record>
</Values>
</MAPTARGET>
  <MAPSOURCE>

<Values version="2.0">
  <record name="xml" javaclass="com.wm.util.Values">
    <value name="node_type">record</value>
    <value name="node_subtype">unknown</value>
    <value name="is_public">false</value>
    <value name="field_type">record</value>
    <value name="field_dim">0</value>
    <value name="nillable">true</value>
    <value name="form_qualified">false</value>
    <value name="is_global">false</value>
    <array name="rec_fields" type="record" depth="1">
      <record javaclass="com.wm.util.Values">
        <value name="node_type">record</value>
        <value name="node_subtype">unknown</value>
        <value name="node_comment"></value>
        <record name="node_hints" javaclass="com.wm.util.Values">
          <value name="field_largerEditor">false</value>
          <value name="field_password">false</value>
        </record>
        <value name="is_public">false</value>
        <value name="field_name">complianceProgram</value>
        <value name="field_type">recref</value>
        <value name="field_dim">0</value>
        <value name="wrapper_type">IData</value>
        <value name="nillable">true</value>
        <value name="form_qualified">false</value>
        <value name="is_global">false</value>
        <value name="rec_closed">true</value>
        <value name="modifiable">true</value>
        <value name="rec_ref">ADESPCompliance.documents:ComplianceProgram</value>
      </record>
      <record javaclass="com.wm.util.Values">
        <value name="node_type">record</value>
        <value name="node_subtype">unknown</value>
        <value name="node_comment"></value>
        <record name="node_hints" javaclass="com.wm.util.Values">
          <value name="field_largerEditor">false</value>
          <value name="field_password">false</value>
        </record>
        <value name="is_public">false</value>
        <value name="field_name">logUserInfo</value>
        <value name="field_type">recref</value>
        <value name="field_dim">0</value>
        <value name="wrapper_type">IData</value>
        <value name="nillable">true</value>
        <value name="form_qualified">false</value>
        <value name="is_global">false</value>
        <value name="rec_closed">true</value>
        <value name="modifiable">true</value>
        <value name="rec_ref">IXLoggingServer.documents:LogUserInformation</value>
      </record>
    </array>
    <value name="modifiable">true</value>
  </record>
</Values>
</MAPSOURCE>

  <!-- nodes -->

<MAPCOPY FROM="/complianceProgram;4;0;ADESPCompliance.documents:ComplianceProgram/id;1;0" TO="/insertComplianceProgramInput;2;0/ID;1;0">
</MAPCOPY>

<MAPCOPY FROM="/complianceProgram;4;0;ADESPCompliance.documents:ComplianceProgram/status;1;0" TO="/insertComplianceProgramInput;2;0/STATUS;1;0">
</MAPCOPY>

<MAPCOPY FROM="/complianceProgram;4;0;ADESPCompliance.documents:ComplianceProgram/year;1;0" TO="/insertComplianceProgramInput;2;0/YEAR;1;0">
</MAPCOPY>

<MAPCOPY FROM="/logUserInfo;4;0;IXLoggingServer.documents:LogUserInformation/userId;1;0" TO="/insertComplianceProgramInput;2;0/MODIFIED_BY;1;0">
</MAPCOPY>

<MAPSET NAME="Setter" OVERWRITE="true" VARIABLES="false" GLOBALVARIABLES="false" FIELD="/insertComplianceProgramInput;2;0/ISACTIVE;1;0">
  <DATA ENCODING="XMLValues" I18N="true">

<Values version="2.0">
  <value name="xml">true</value>
  <record name="type" javaclass="com.wm.util.Values">
    <value name="node_type">unknown</value>
    <value name="node_subtype">unknown</value>
    <value name="is_public">false</value>
    <value name="field_name">ISACTIVE</value>
    <value name="field_type">string</value>
    <value name="field_dim">0</value>
    <value name="nillable">true</value>
    <value name="form_qualified">false</value>
    <value name="is_global">false</value>
  </record>
</Values>
</DATA>
</MAPSET>

<MAPCOPY FROM="/complianceProgram;4;0;ADESPCompliance.documents:ComplianceProgram/programName;1;0" TO="/insertComplianceProgramInput;2;0/PROGRAMME_NAME;1;0">
</MAPCOPY>
</MAP>

<MAP MODE="OUTPUT">
  <MAPTARGET>

<Values version="2.0">
  <record name="xml" javaclass="com.wm.util.Values">
    <value name="node_type">record</value>
    <value name="node_subtype">unknown</value>
    <value name="is_public">false</value>
    <value name="field_type">record</value>
    <value name="field_dim">0</value>
    <value name="nillable">true</value>
    <value name="form_qualified">false</value>
    <value name="is_global">false</value>
    <array name="rec_fields" type="record" depth="1">
      <record javaclass="com.wm.util.Values">
        <value name="node_type">record</value>
        <value name="node_subtype">unknown</value>
        <value name="is_public">false</value>
        <value name="field_name">insertComplianceProgramInput</value>
        <value name="field_type">record</value>
        <value name="field_dim">0</value>
        <value name="nillable">true</value>
        <value name="form_qualified">false</value>
        <value name="is_global">false</value>
        <array name="rec_fields" type="record" depth="1">
          <record javaclass="com.wm.util.Values">
            <value name="node_type">unknown</value>
            <value name="node_subtype">unknown</value>
            <value name="is_public">false</value>
            <value name="field_name">ID</value>
            <value name="field_type">string</value>
            <value name="field_dim">0</value>
            <value name="nillable">true</value>
            <value name="form_qualified">false</value>
            <value name="is_global">false</value>
          </record>
          <record javaclass="com.wm.util.Values">
            <value name="node_type">unknown</value>
            <value name="node_subtype">unknown</value>
            <value name="is_public">false</value>
            <value name="field_name">PROGRAMME_NAME</value>
            <value name="field_type">string</value>
            <value name="field_dim">0</value>
            <value name="nillable">true</value>
            <value name="form_qualified">false</value>
            <value name="is_global">false</value>
          </record>
          <record javaclass="com.wm.util.Values">
            <value name="node_type">unknown</value>
            <value name="node_subtype">unknown</value>
            <value name="is_public">false</value>
            <value name="field_name">MODIFIED_BY</value>
            <value name="field_type">string</value>
            <value name="field_dim">0</value>
            <value name="nillable">true</value>
            <value name="form_qualified">false</value>
            <value name="is_global">false</value>
          </record>
          <record javaclass="com.wm.util.Values">
            <value name="node_type">unknown</value>
            <value name="node_subtype">unknown</value>
            <value name="is_public">false</value>
            <value name="field_name">STATUS</value>
            <value name="field_type">string</value>
            <value name="field_dim">0</value>
            <value name="nillable">true</value>
            <value name="form_qualified">false</value>
            <value name="is_global">false</value>
          </record>
          <record javaclass="com.wm.util.Values">
            <value name="node_type">unknown</value>
            <value name="node_subtype">unknown</value>
            <value name="is_public">false</value>
            <value name="field_name">ISACTIVE</value>
            <value name="field_type">string</value>
            <value name="field_dim">0</value>
            <value name="nillable">true</value>
            <value name="form_qualified">false</value>
            <value name="is_global">false</value>
          </record>
          <record javaclass="com.wm.util.Values">
            <value name="node_type">unknown</value>
            <value name="node_subtype">unknown</value>
            <value name="is_public">false</value>
            <value name="field_name">YEAR</value>
            <value name="field_type">string</value>
            <value name="field_dim">0</value>
            <value name="nillable">true</value>
            <value name="form_qualified">false</value>
            <value name="is_global">false</value>
          </record>
        </array>
        <value name="modifiable">true</value>
      </record>
      <record javaclass="com.wm.util.Values">
        <value name="node_type">record</value>
        <value name="node_subtype">unknown</value>
        <value name="node_comment"></value>
        <record name="node_hints" javaclass="com.wm.util.Values">
          <value name="field_largerEditor">false</value>
          <value name="field_password">false</value>
        </record>
        <value name="is_public">false</value>
        <value name="field_name">complianceProgram</value>
        <value name="field_type">recref</value>
        <value name="field_dim">0</value>
        <value name="wrapper_type">IData</value>
        <value name="nillable">true</value>
        <value name="form_qualified">false</value>
        <value name="is_global">false</value>
        <value name="rec_closed">true</value>
        <value name="modifiable">true</value>
        <value name="rec_ref">ADESPCompliance.documents:ComplianceProgram</value>
      </record>
      <record javaclass="com.wm.util.Values">
        <value name="node_type">record</value>
        <value name="node_subtype">unknown</value>
        <value name="node_comment"></value>
        <record name="node_hints" javaclass="com.wm.util.Values">
          <value name="field_largerEditor">false</value>
          <value name="field_password">false</value>
        </record>
        <value name="is_public">false</value>
        <value name="field_name">logUserInfo</value>
        <value name="field_type">recref</value>
        <value name="field_dim">0</value>
        <value name="wrapper_type">IData</value>
        <value name="nillable">true</value>
        <value name="form_qualified">false</value>
        <value name="is_global">false</value>
        <value name="rec_closed">true</value>
        <value name="modifiable">true</value>
        <value name="rec_ref">IXLoggingServer.documents:LogUserInformation</value>
      </record>
      <record javaclass="com.wm.util.Values">
        <value name="node_type">record</value>
        <value name="node_subtype">unknown</value>
        <value name="is_public">false</value>
        <value name="field_name">insertComplianceProgramOutput</value>
        <value name="field_type">record</value>
        <value name="field_dim">0</value>
        <value name="nillable">true</value>
        <value name="form_qualified">false</value>
        <value name="is_global">false</value>
        <array name="rec_fields" type="record" depth="1">
        </array>
        <value name="modifiable">true</value>
      </record>
    </array>
    <value name="modifiable">true</value>
  </record>
</Values>
</MAPTARGET>
  <MAPSOURCE>

<Values version="2.0">
  <record name="xml" javaclass="com.wm.util.Values">
    <value name="node_type">record</value>
    <value name="node_subtype">unknown</value>
    <value name="is_public">false</value>
    <value name="field_name">insertComplianceProgramOutput</value>
    <value name="field_type">record</value>
    <value name="field_dim">0</value>
    <value name="nillable">true</value>
    <value name="form_qualified">false</value>
    <value name="is_global">false</value>
    <array name="rec_fields" type="record" depth="1">
      <record javaclass="com.wm.util.Values">
        <value name="node_type">record</value>
        <value name="node_subtype">unknown</value>
        <value name="is_public">false</value>
        <value name="field_name">insertComplianceProgramOutput</value>
        <value name="field_type">record</value>
        <value name="field_dim">0</value>
        <value name="nillable">true</value>
        <value name="form_qualified">false</value>
        <value name="is_global">false</value>
        <array name="rec_fields" type="record" depth="1">
        </array>
        <value name="modifiable">true</value>
      </record>
    </array>
    <value name="modifiable">true</value>
  </record>
</Values>
</MAPSOURCE>

  <!-- nodes -->

<MAPDELETE FIELD="/insertComplianceProgramOutput;2;0">
</MAPDELETE>

<MAPDELETE FIELD="/insertComplianceProgramInput;2;0">
</MAPDELETE>
</MAP>
</INVOKE>
</SEQUENCE>
</BRANCH>

<INVOKE TIMEOUT="" SERVICE="ADESPCompliance.adapters.complianceProgram:deleteComplianceRegulatoryActivities" VALIDATE-IN="$none" VALIDATE-OUT="$none">
  <COMMENT></COMMENT>

  <!-- nodes -->

<MAP MODE="INPUT">
  <MAPTARGET>

<Values version="2.0">
  <record name="xml" javaclass="com.wm.util.Values">
    <value name="node_type">record</value>
    <value name="node_subtype">unknown</value>
    <value name="is_public">false</value>
    <value name="field_name">deleteComplianceRegulatoryActivitiesInput</value>
    <value name="field_type">record</value>
    <value name="field_dim">0</value>
    <value name="nillable">true</value>
    <value name="form_qualified">false</value>
    <value name="is_global">false</value>
    <array name="rec_fields" type="record" depth="1">
      <record javaclass="com.wm.util.Values">
        <value name="node_type">record</value>
        <value name="node_subtype">unknown</value>
        <value name="is_public">false</value>
        <value name="field_name">deleteComplianceRegulatoryActivitiesInput</value>
        <value name="field_type">record</value>
        <value name="field_dim">0</value>
        <value name="nillable">true</value>
        <value name="form_qualified">false</value>
        <value name="is_global">false</value>
        <array name="rec_fields" type="record" depth="1">
          <record javaclass="com.wm.util.Values">
            <value name="node_type">record</value>
            <value name="node_subtype">unknown</value>
            <value name="is_public">false</value>
            <value name="field_name">overrideCredentials</value>
            <value name="field_type">record</value>
            <value name="field_dim">0</value>
            <value name="nillable">true</value>
            <value name="form_qualified">false</value>
            <value name="is_global">false</value>
            <array name="rec_fields" type="record" depth="1">
            </array>
            <value name="modifiable">true</value>
          </record>
          <record javaclass="com.wm.util.Values">
            <value name="node_type">unknown</value>
            <value name="node_subtype">unknown</value>
            <value name="is_public">false</value>
            <value name="field_name">COMPLIANCE_ID</value>
            <value name="field_type">string</value>
            <value name="field_dim">0</value>
            <value name="nillable">true</value>
            <value name="form_qualified">false</value>
            <value name="is_global">false</value>
          </record>
        </array>
        <value name="modifiable">true</value>
      </record>
      <record javaclass="com.wm.util.Values">
        <value name="node_type">record</value>
        <value name="node_subtype">unknown</value>
        <value name="is_public">false</value>
        <value name="field_name">$connectionName</value>
        <value name="field_type">string</value>
        <value name="field_dim">0</value>
        <value name="field_opt">true</value>
        <value name="nillable">false</value>
        <value name="form_qualified">false</value>
        <value name="is_global">false</value>
      </record>
    </array>
    <value name="modifiable">true</value>
  </record>
</Values>
</MAPTARGET>
  <MAPSOURCE>

<Values version="2.0">
  <record name="xml" javaclass="com.wm.util.Values">
    <value name="node_type">record</value>
    <value name="node_subtype">unknown</value>
    <value name="is_public">false</value>
    <value name="field_type">record</value>
    <value name="field_dim">0</value>
    <value name="nillable">true</value>
    <value name="form_qualified">false</value>
    <value name="is_global">false</value>
    <array name="rec_fields" type="record" depth="1">
      <record javaclass="com.wm.util.Values">
        <value name="node_type">record</value>
        <value name="node_subtype">unknown</value>
        <value name="node_comment"></value>
        <record name="node_hints" javaclass="com.wm.util.Values">
          <value name="field_largerEditor">false</value>
          <value name="field_password">false</value>
        </record>
        <value name="is_public">false</value>
        <value name="field_name">complianceProgram</value>
        <value name="field_type">recref</value>
        <value name="field_dim">0</value>
        <value name="wrapper_type">IData</value>
        <value name="nillable">true</value>
        <value name="form_qualified">false</value>
        <value name="is_global">false</value>
        <value name="rec_closed">true</value>
        <value name="modifiable">true</value>
        <value name="rec_ref">ADESPCompliance.documents:ComplianceProgram</value>
      </record>
      <record javaclass="com.wm.util.Values">
        <value name="node_type">record</value>
        <value name="node_subtype">unknown</value>
        <value name="node_comment"></value>
        <record name="node_hints" javaclass="com.wm.util.Values">
          <value name="field_largerEditor">false</value>
          <value name="field_password">false</value>
        </record>
        <value name="is_public">false</value>
        <value name="field_name">logUserInfo</value>
        <value name="field_type">recref</value>
        <value name="field_dim">0</value>
        <value name="wrapper_type">IData</value>
        <value name="nillable">true</value>
        <value name="form_qualified">false</value>
        <value name="is_global">false</value>
        <value name="rec_closed">true</value>
        <value name="modifiable">true</value>
        <value name="rec_ref">IXLoggingServer.documents:LogUserInformation</value>
      </record>
    </array>
    <value name="modifiable">true</value>
  </record>
</Values>
</MAPSOURCE>

  <!-- nodes -->

<MAPCOPY FROM="/complianceProgram;4;0;ADESPCompliance.documents:ComplianceProgram/id;1;0" TO="/deleteComplianceRegulatoryActivitiesInput;2;0/COMPLIANCE_ID;1;0">
</MAPCOPY>
</MAP>

<MAP MODE="OUTPUT">
  <MAPTARGET>

<Values version="2.0">
  <record name="xml" javaclass="com.wm.util.Values">
    <value name="node_type">record</value>
    <value name="node_subtype">unknown</value>
    <value name="is_public">false</value>
    <value name="field_type">record</value>
    <value name="field_dim">0</value>
    <value name="nillable">true</value>
    <value name="form_qualified">false</value>
    <value name="is_global">false</value>
    <array name="rec_fields" type="record" depth="1">
      <record javaclass="com.wm.util.Values">
        <value name="node_type">record</value>
        <value name="node_subtype">unknown</value>
        <value name="is_public">false</value>
        <value name="field_name">deleteComplianceRegulatoryActivitiesInput</value>
        <value name="field_type">record</value>
        <value name="field_dim">0</value>
        <value name="nillable">true</value>
        <value name="form_qualified">false</value>
        <value name="is_global">false</value>
        <array name="rec_fields" type="record" depth="1">
          <record javaclass="com.wm.util.Values">
            <value name="node_type">unknown</value>
            <value name="node_subtype">unknown</value>
            <value name="is_public">false</value>
            <value name="field_name">COMPLIANCE_ID</value>
            <value name="field_type">string</value>
            <value name="field_dim">0</value>
            <value name="nillable">true</value>
            <value name="form_qualified">false</value>
            <value name="is_global">false</value>
          </record>
        </array>
        <value name="modifiable">true</value>
      </record>
      <record javaclass="com.wm.util.Values">
        <value name="node_type">record</value>
        <value name="node_subtype">unknown</value>
        <value name="node_comment"></value>
        <record name="node_hints" javaclass="com.wm.util.Values">
          <value name="field_largerEditor">false</value>
          <value name="field_password">false</value>
        </record>
        <value name="is_public">false</value>
        <value name="field_name">complianceProgram</value>
        <value name="field_type">recref</value>
        <value name="field_dim">0</value>
        <value name="wrapper_type">IData</value>
        <value name="nillable">true</value>
        <value name="form_qualified">false</value>
        <value name="is_global">false</value>
        <value name="rec_closed">true</value>
        <value name="modifiable">true</value>
        <value name="rec_ref">ADESPCompliance.documents:ComplianceProgram</value>
      </record>
      <record javaclass="com.wm.util.Values">
        <value name="node_type">record</value>
        <value name="node_subtype">unknown</value>
        <value name="node_comment"></value>
        <record name="node_hints" javaclass="com.wm.util.Values">
          <value name="field_largerEditor">false</value>
          <value name="field_password">false</value>
        </record>
        <value name="is_public">false</value>
        <value name="field_name">logUserInfo</value>
        <value name="field_type">recref</value>
        <value name="field_dim">0</value>
        <value name="wrapper_type">IData</value>
        <value name="nillable">true</value>
        <value name="form_qualified">false</value>
        <value name="is_global">false</value>
        <value name="rec_closed">true</value>
        <value name="modifiable">true</value>
        <value name="rec_ref">IXLoggingServer.documents:LogUserInformation</value>
      </record>
      <record javaclass="com.wm.util.Values">
        <value name="node_type">record</value>
        <value name="node_subtype">unknown</value>
        <value name="is_public">false</value>
        <value name="field_name">deleteComplianceRegulatoryActivitiesOutput</value>
        <value name="field_type">record</value>
        <value name="field_dim">0</value>
        <value name="nillable">true</value>
        <value name="form_qualified">false</value>
        <value name="is_global">false</value>
        <array name="rec_fields" type="record" depth="1">
        </array>
        <value name="modifiable">true</value>
      </record>
    </array>
    <value name="modifiable">true</value>
  </record>
</Values>
</MAPTARGET>
  <MAPSOURCE>

<Values version="2.0">
  <record name="xml" javaclass="com.wm.util.Values">
    <value name="node_type">record</value>
    <value name="node_subtype">unknown</value>
    <value name="is_public">false</value>
    <value name="field_name">deleteComplianceRegulatoryActivitiesOutput</value>
    <value name="field_type">record</value>
    <value name="field_dim">0</value>
    <value name="nillable">true</value>
    <value name="form_qualified">false</value>
    <value name="is_global">false</value>
    <array name="rec_fields" type="record" depth="1">
      <record javaclass="com.wm.util.Values">
        <value name="node_type">record</value>
        <value name="node_subtype">unknown</value>
        <value name="is_public">false</value>
        <value name="field_name">deleteComplianceRegulatoryActivitiesOutput</value>
        <value name="field_type">record</value>
        <value name="field_dim">0</value>
        <value name="nillable">true</value>
        <value name="form_qualified">false</value>
        <value name="is_global">false</value>
        <array name="rec_fields" type="record" depth="1">
        </array>
        <value name="modifiable">true</value>
      </record>
    </array>
    <value name="modifiable">true</value>
  </record>
</Values>
</MAPSOURCE>

  <!-- nodes -->

<MAPDELETE FIELD="/deleteComplianceRegulatoryActivitiesOutput;2;0">
</MAPDELETE>

<MAPDELETE FIELD="/deleteComplianceRegulatoryActivitiesInput;2;0">
</MAPDELETE>
</MAP>
</INVOKE>

<LOOP TIMEOUT="" IN-ARRAY="/complianceProgram/complianceRegulatedActivities">
  <COMMENT></COMMENT>

  <!-- nodes -->

<SEQUENCE TIMEOUT="" EXIT-ON="FAILURE">
  <COMMENT></COMMENT>

  <!-- nodes -->

<INVOKE TIMEOUT="" SERVICE="IXCommon.maps:getSeqId" VALIDATE-IN="$none" VALIDATE-OUT="$none">
  <COMMENT>==</COMMENT>

  <!-- nodes -->

<MAP MODE="INPUT">
  <MAPTARGET>

<Values version="2.0">
  <record name="xml" javaclass="com.wm.util.Values">
    <value name="node_type">record</value>
    <value name="node_subtype">unknown</value>
    <value name="is_public">false</value>
    <value name="field_type">record</value>
    <value name="field_dim">0</value>
    <value name="wrapper_type">IData</value>
    <value name="nillable">true</value>
    <value name="form_qualified">false</value>
    <value name="is_global">false</value>
    <array name="rec_fields" type="record" depth="1">
      <record javaclass="com.wm.util.Values">
        <value name="node_type">record</value>
        <value name="node_subtype">unknown</value>
        <value name="node_comment"></value>
        <record name="node_hints" javaclass="com.wm.util.Values">
          <value name="field_usereditable">true</value>
          <value name="field_largerEditor">false</value>
          <value name="field_password">false</value>
        </record>
        <value name="is_public">false</value>
        <value name="field_name">seqName</value>
        <value name="field_type">string</value>
        <value name="field_dim">0</value>
        <array name="field_options" type="value" depth="1">
        </array>
        <value name="nillable">true</value>
        <value name="form_qualified">false</value>
        <value name="is_global">false</value>
      </record>
    </array>
    <value name="modifiable">true</value>
  </record>
</Values>
</MAPTARGET>
  <MAPSOURCE>

<Values version="2.0">
  <record name="xml" javaclass="com.wm.util.Values">
    <value name="node_type">record</value>
    <value name="node_subtype">unknown</value>
    <value name="is_public">false</value>
    <value name="field_type">record</value>
    <value name="field_dim">0</value>
    <value name="nillable">true</value>
    <value name="form_qualified">false</value>
    <value name="is_global">false</value>
    <array name="rec_fields" type="record" depth="1">
    </array>
    <value name="modifiable">true</value>
  </record>
</Values>
</MAPSOURCE>

  <!-- nodes -->

<MAPSET NAME="Setter" OVERWRITE="true" VARIABLES="false" GLOBALVARIABLES="false" FIELD="/seqName;1;0">
  <DATA ENCODING="XMLValues" I18N="true">

<Values version="2.0">
  <value name="xml">COMPLIANCE_REGULATED_ACTIVITY_SEQ</value>
  <record name="type" javaclass="com.wm.util.Values">
    <value name="node_type">record</value>
    <value name="node_subtype">unknown</value>
    <value name="node_comment"></value>
    <record name="node_hints" javaclass="com.wm.util.Values">
      <value name="field_usereditable">true</value>
      <value name="field_largerEditor">false</value>
      <value name="field_password">false</value>
    </record>
    <value name="is_public">false</value>
    <value name="field_name">seqName</value>
    <value name="field_type">string</value>
    <value name="field_dim">0</value>
    <array name="field_options" type="value" depth="1">
    </array>
    <value name="nillable">true</value>
    <value name="form_qualified">false</value>
    <value name="is_global">false</value>
  </record>
</Values>
</DATA>
</MAPSET>
</MAP>

<MAP MODE="OUTPUT">
  <MAPTARGET>

<Values version="2.0">
  <record name="xml" javaclass="com.wm.util.Values">
    <value name="node_type">record</value>
    <value name="node_subtype">unknown</value>
    <value name="is_public">false</value>
    <value name="field_type">record</value>
    <value name="field_dim">0</value>
    <value name="nillable">true</value>
    <value name="form_qualified">false</value>
    <value name="is_global">false</value>
    <array name="rec_fields" type="record" depth="1">
      <record javaclass="com.wm.util.Values">
        <value name="node_type">unknown</value>
        <value name="node_subtype">unknown</value>
        <value name="is_public">false</value>
        <value name="field_name">seqName</value>
        <value name="field_type">string</value>
        <value name="field_dim">0</value>
        <value name="nillable">true</value>
        <value name="form_qualified">false</value>
        <value name="is_global">false</value>
      </record>
      <record javaclass="com.wm.util.Values">
        <value name="node_type">record</value>
        <value name="node_subtype">unknown</value>
        <value name="node_comment"></value>
        <record name="node_hints" javaclass="com.wm.util.Values">
          <value name="field_largerEditor">false</value>
          <value name="field_password">false</value>
        </record>
        <value name="is_public">false</value>
        <value name="field_name">complianceProgram</value>
        <value name="field_type">recref</value>
        <value name="field_dim">0</value>
        <value name="wrapper_type">IData</value>
        <value name="nillable">true</value>
        <value name="form_qualified">false</value>
        <value name="is_global">false</value>
        <value name="rec_closed">true</value>
        <value name="modifiable">true</value>
        <value name="rec_ref">ADESPCompliance.documents:ComplianceProgram</value>
      </record>
      <record javaclass="com.wm.util.Values">
        <value name="node_type">record</value>
        <value name="node_subtype">unknown</value>
        <value name="node_comment"></value>
        <record name="node_hints" javaclass="com.wm.util.Values">
          <value name="field_largerEditor">false</value>
          <value name="field_password">false</value>
        </record>
        <value name="is_public">false</value>
        <value name="field_name">logUserInfo</value>
        <value name="field_type">recref</value>
        <value name="field_dim">0</value>
        <value name="wrapper_type">IData</value>
        <value name="nillable">true</value>
        <value name="form_qualified">false</value>
        <value name="is_global">false</value>
        <value name="rec_closed">true</value>
        <value name="modifiable">true</value>
        <value name="rec_ref">IXLoggingServer.documents:LogUserInformation</value>
      </record>
      <record javaclass="com.wm.util.Values">
        <value name="node_type">record</value>
        <value name="node_subtype">unknown</value>
        <value name="node_comment"></value>
        <record name="node_hints" javaclass="com.wm.util.Values">
          <value name="field_usereditable">true</value>
          <value name="field_largerEditor">false</value>
          <value name="field_password">false</value>
        </record>
        <value name="is_public">false</value>
        <value name="field_name">seqId</value>
        <value name="field_type">string</value>
        <value name="field_dim">0</value>
        <array name="field_options" type="value" depth="1">
        </array>
        <value name="nillable">true</value>
        <value name="form_qualified">false</value>
        <value name="is_global">false</value>
      </record>
    </array>
    <value name="modifiable">true</value>
  </record>
</Values>
</MAPTARGET>
  <MAPSOURCE>

<Values version="2.0">
  <record name="xml" javaclass="com.wm.util.Values">
    <value name="node_type">record</value>
    <value name="node_subtype">unknown</value>
    <value name="is_public">false</value>
    <value name="field_type">record</value>
    <value name="field_dim">0</value>
    <value name="wrapper_type">IData</value>
    <value name="nillable">true</value>
    <value name="form_qualified">false</value>
    <value name="is_global">false</value>
    <array name="rec_fields" type="record" depth="1">
      <record javaclass="com.wm.util.Values">
        <value name="node_type">record</value>
        <value name="node_subtype">unknown</value>
        <value name="node_comment"></value>
        <record name="node_hints" javaclass="com.wm.util.Values">
          <value name="field_usereditable">true</value>
          <value name="field_largerEditor">false</value>
          <value name="field_password">false</value>
        </record>
        <value name="is_public">false</value>
        <value name="field_name">seqId</value>
        <value name="field_type">string</value>
        <value name="field_dim">0</value>
        <array name="field_options" type="value" depth="1">
        </array>
        <value name="nillable">true</value>
        <value name="form_qualified">false</value>
        <value name="is_global">false</value>
      </record>
    </array>
    <value name="modifiable">true</value>
  </record>
</Values>
</MAPSOURCE>

  <!-- nodes -->

<MAPDELETE FIELD="/seqId;1;0">
</MAPDELETE>

<MAPDELETE FIELD="/seqName;1;0">
</MAPDELETE>

<MAPCOPY FROM="/seqId;1;0" TO="/complianceProgram;4;0;ADESPCompliance.documents:ComplianceProgram/complianceRegulatedActivities;4;0;ADESPCompliance.documents:ComplianceRegulatedActivities/id;1;0">
</MAPCOPY>
</MAP>
</INVOKE>

<INVOKE TIMEOUT="" SERVICE="ADESPCompliance.adapters.complianceProgram:insertComplianceRegulatedActivity" VALIDATE-IN="$none" VALIDATE-OUT="$none">
  <COMMENT></COMMENT>

  <!-- nodes -->

<MAP MODE="INPUT">
  <MAPTARGET>

<Values version="2.0">
  <record name="xml" javaclass="com.wm.util.Values">
    <value name="node_type">record</value>
    <value name="node_subtype">unknown</value>
    <value name="is_public">false</value>
    <value name="field_name">insertRegulatedActivityInput</value>
    <value name="field_type">record</value>
    <value name="field_dim">0</value>
    <value name="nillable">true</value>
    <value name="form_qualified">false</value>
    <value name="is_global">false</value>
    <array name="rec_fields" type="record" depth="1">
      <record javaclass="com.wm.util.Values">
        <value name="node_type">record</value>
        <value name="node_subtype">unknown</value>
        <value name="is_public">false</value>
        <value name="field_name">insertRegulatedActivityInput</value>
        <value name="field_type">record</value>
        <value name="field_dim">0</value>
        <value name="nillable">true</value>
        <value name="form_qualified">false</value>
        <value name="is_global">false</value>
        <array name="rec_fields" type="record" depth="1">
          <record javaclass="com.wm.util.Values">
            <value name="node_type">record</value>
            <value name="node_subtype">unknown</value>
            <value name="is_public">false</value>
            <value name="field_name">overrideCredentials</value>
            <value name="field_type">record</value>
            <value name="field_dim">0</value>
            <value name="nillable">true</value>
            <value name="form_qualified">false</value>
            <value name="is_global">false</value>
            <array name="rec_fields" type="record" depth="1">
            </array>
            <value name="modifiable">true</value>
          </record>
          <record javaclass="com.wm.util.Values">
            <value name="node_type">unknown</value>
            <value name="node_subtype">unknown</value>
            <value name="is_public">false</value>
            <value name="field_name">ID</value>
            <value name="field_type">string</value>
            <value name="field_dim">0</value>
            <value name="nillable">true</value>
            <value name="form_qualified">false</value>
            <value name="is_global">false</value>
          </record>
          <record javaclass="com.wm.util.Values">
            <value name="node_type">unknown</value>
            <value name="node_subtype">unknown</value>
            <value name="is_public">false</value>
            <value name="field_name">COMPLIANCE_ID</value>
            <value name="field_type">string</value>
            <value name="field_dim">0</value>
            <value name="nillable">true</value>
            <value name="form_qualified">false</value>
            <value name="is_global">false</value>
          </record>
          <record javaclass="com.wm.util.Values">
            <value name="node_type">unknown</value>
            <value name="node_subtype">unknown</value>
            <value name="is_public">false</value>
            <value name="field_name">REGULATED_ACTIVITIES_TYPE</value>
            <value name="field_type">string</value>
            <value name="field_dim">0</value>
            <value name="nillable">true</value>
            <value name="form_qualified">false</value>
            <value name="is_global">false</value>
          </record>
        </array>
        <value name="modifiable">true</value>
      </record>
      <record javaclass="com.wm.util.Values">
        <value name="node_type">record</value>
        <value name="node_subtype">unknown</value>
        <value name="is_public">false</value>
        <value name="field_name">$connectionName</value>
        <value name="field_type">string</value>
        <value name="field_dim">0</value>
        <value name="field_opt">true</value>
        <value name="nillable">false</value>
        <value name="form_qualified">false</value>
        <value name="is_global">false</value>
      </record>
    </array>
    <value name="modifiable">true</value>
  </record>
</Values>
</MAPTARGET>
  <MAPSOURCE>

<Values version="2.0">
  <record name="xml" javaclass="com.wm.util.Values">
    <value name="node_type">record</value>
    <value name="node_subtype">unknown</value>
    <value name="is_public">false</value>
    <value name="field_type">record</value>
    <value name="field_dim">0</value>
    <value name="nillable">true</value>
    <value name="form_qualified">false</value>
    <value name="is_global">false</value>
    <array name="rec_fields" type="record" depth="1">
      <record javaclass="com.wm.util.Values">
        <value name="node_type">record</value>
        <value name="node_subtype">unknown</value>
        <value name="node_comment"></value>
        <record name="node_hints" javaclass="com.wm.util.Values">
          <value name="field_largerEditor">false</value>
          <value name="field_password">false</value>
        </record>
        <value name="is_public">false</value>
        <value name="field_name">complianceProgram</value>
        <value name="field_type">recref</value>
        <value name="field_dim">0</value>
        <value name="wrapper_type">IData</value>
        <value name="nillable">true</value>
        <value name="form_qualified">false</value>
        <value name="is_global">false</value>
        <value name="rec_closed">true</value>
        <value name="modifiable">true</value>
        <value name="rec_ref">ADESPCompliance.documents:ComplianceProgram</value>
      </record>
      <record javaclass="com.wm.util.Values">
        <value name="node_type">record</value>
        <value name="node_subtype">unknown</value>
        <value name="node_comment"></value>
        <record name="node_hints" javaclass="com.wm.util.Values">
          <value name="field_largerEditor">false</value>
          <value name="field_password">false</value>
        </record>
        <value name="is_public">false</value>
        <value name="field_name">logUserInfo</value>
        <value name="field_type">recref</value>
        <value name="field_dim">0</value>
        <value name="wrapper_type">IData</value>
        <value name="nillable">true</value>
        <value name="form_qualified">false</value>
        <value name="is_global">false</value>
        <value name="rec_closed">true</value>
        <value name="modifiable">true</value>
        <value name="rec_ref">IXLoggingServer.documents:LogUserInformation</value>
      </record>
      <record javaclass="com.wm.util.Values">
        <value name="node_type">unknown</value>
        <value name="node_subtype">unknown</value>
        <value name="is_public">false</value>
        <value name="field_name">$iteration</value>
        <value name="field_type">string</value>
        <value name="field_dim">0</value>
        <value name="nillable">true</value>
        <value name="form_qualified">false</value>
        <value name="is_global">false</value>
      </record>
    </array>
    <value name="modifiable">true</value>
  </record>
</Values>
</MAPSOURCE>

  <!-- nodes -->

<MAPCOPY FROM="/complianceProgram;4;0;ADESPCompliance.documents:ComplianceProgram/complianceRegulatedActivities;4;0;ADESPCompliance.documents:ComplianceRegulatedActivities/id;1;0" TO="/insertRegulatedActivityInput;2;0/ID;1;0">
</MAPCOPY>

<MAPCOPY FROM="/complianceProgram;4;0;ADESPCompliance.documents:ComplianceProgram/complianceRegulatedActivities;4;0;ADESPCompliance.documents:ComplianceRegulatedActivities/regulatedActivityType;1;0" TO="/insertRegulatedActivityInput;2;0/REGULATED_ACTIVITIES_TYPE;1;0">
</MAPCOPY>

<MAPCOPY FROM="/complianceProgram;4;0;ADESPCompliance.documents:ComplianceProgram/id;1;0" TO="/insertRegulatedActivityInput;2;0/COMPLIANCE_ID;1;0">
</MAPCOPY>
</MAP>

<MAP MODE="OUTPUT">
  <MAPTARGET>

<Values version="2.0">
  <record name="xml" javaclass="com.wm.util.Values">
    <value name="node_type">record</value>
    <value name="node_subtype">unknown</value>
    <value name="is_public">false</value>
    <value name="field_type">record</value>
    <value name="field_dim">0</value>
    <value name="nillable">true</value>
    <value name="form_qualified">false</value>
    <value name="is_global">false</value>
    <array name="rec_fields" type="record" depth="1">
      <record javaclass="com.wm.util.Values">
        <value name="node_type">record</value>
        <value name="node_subtype">unknown</value>
        <value name="is_public">false</value>
        <value name="field_name">insertRegulatedActivityInput</value>
        <value name="field_type">record</value>
        <value name="field_dim">0</value>
        <value name="nillable">true</value>
        <value name="form_qualified">false</value>
        <value name="is_global">false</value>
        <array name="rec_fields" type="record" depth="1">
          <record javaclass="com.wm.util.Values">
            <value name="node_type">unknown</value>
            <value name="node_subtype">unknown</value>
            <value name="is_public">false</value>
            <value name="field_name">ID</value>
            <value name="field_type">string</value>
            <value name="field_dim">0</value>
            <value name="nillable">true</value>
            <value name="form_qualified">false</value>
            <value name="is_global">false</value>
          </record>
          <record javaclass="com.wm.util.Values">
            <value name="node_type">unknown</value>
            <value name="node_subtype">unknown</value>
            <value name="is_public">false</value>
            <value name="field_name">COMPLIANCE_ID</value>
            <value name="field_type">string</value>
            <value name="field_dim">0</value>
            <value name="nillable">true</value>
            <value name="form_qualified">false</value>
            <value name="is_global">false</value>
          </record>
          <record javaclass="com.wm.util.Values">
            <value name="node_type">unknown</value>
            <value name="node_subtype">unknown</value>
            <value name="is_public">false</value>
            <value name="field_name">REGULATED_ACTIVITIES_TYPE</value>
            <value name="field_type">string</value>
            <value name="field_dim">0</value>
            <value name="nillable">true</value>
            <value name="form_qualified">false</value>
            <value name="is_global">false</value>
          </record>
        </array>
        <value name="modifiable">true</value>
      </record>
      <record javaclass="com.wm.util.Values">
        <value name="node_type">record</value>
        <value name="node_subtype">unknown</value>
        <value name="node_comment"></value>
        <record name="node_hints" javaclass="com.wm.util.Values">
          <value name="field_largerEditor">false</value>
          <value name="field_password">false</value>
        </record>
        <value name="is_public">false</value>
        <value name="field_name">complianceProgram</value>
        <value name="field_type">recref</value>
        <value name="field_dim">0</value>
        <value name="wrapper_type">IData</value>
        <value name="nillable">true</value>
        <value name="form_qualified">false</value>
        <value name="is_global">false</value>
        <value name="rec_closed">true</value>
        <value name="modifiable">true</value>
        <value name="rec_ref">ADESPCompliance.documents:ComplianceProgram</value>
      </record>
      <record javaclass="com.wm.util.Values">
        <value name="node_type">record</value>
        <value name="node_subtype">unknown</value>
        <value name="node_comment"></value>
        <record name="node_hints" javaclass="com.wm.util.Values">
          <value name="field_largerEditor">false</value>
          <value name="field_password">false</value>
        </record>
        <value name="is_public">false</value>
        <value name="field_name">logUserInfo</value>
        <value name="field_type">recref</value>
        <value name="field_dim">0</value>
        <value name="wrapper_type">IData</value>
        <value name="nillable">true</value>
        <value name="form_qualified">false</value>
        <value name="is_global">false</value>
        <value name="rec_closed">true</value>
        <value name="modifiable">true</value>
        <value name="rec_ref">IXLoggingServer.documents:LogUserInformation</value>
      </record>
      <record javaclass="com.wm.util.Values">
        <value name="node_type">record</value>
        <value name="node_subtype">unknown</value>
        <value name="is_public">false</value>
        <value name="field_name">insertRegulatedActivityOutput</value>
        <value name="field_type">record</value>
        <value name="field_dim">0</value>
        <value name="nillable">true</value>
        <value name="form_qualified">false</value>
        <value name="is_global">false</value>
        <array name="rec_fields" type="record" depth="1">
        </array>
        <value name="modifiable">true</value>
      </record>
    </array>
    <value name="modifiable">true</value>
  </record>
</Values>
</MAPTARGET>
  <MAPSOURCE>

<Values version="2.0">
  <record name="xml" javaclass="com.wm.util.Values">
    <value name="node_type">record</value>
    <value name="node_subtype">unknown</value>
    <value name="is_public">false</value>
    <value name="field_name">insertRegulatedActivityOutput</value>
    <value name="field_type">record</value>
    <value name="field_dim">0</value>
    <value name="nillable">true</value>
    <value name="form_qualified">false</value>
    <value name="is_global">false</value>
    <array name="rec_fields" type="record" depth="1">
      <record javaclass="com.wm.util.Values">
        <value name="node_type">record</value>
        <value name="node_subtype">unknown</value>
        <value name="is_public">false</value>
        <value name="field_name">insertRegulatedActivityOutput</value>
        <value name="field_type">record</value>
        <value name="field_dim">0</value>
        <value name="nillable">true</value>
        <value name="form_qualified">false</value>
        <value name="is_global">false</value>
        <array name="rec_fields" type="record" depth="1">
        </array>
        <value name="modifiable">true</value>
      </record>
    </array>
    <value name="modifiable">true</value>
  </record>
</Values>
</MAPSOURCE>

  <!-- nodes -->

<MAPDELETE FIELD="/insertRegulatedActivityOutput;2;0">
</MAPDELETE>

<MAPDELETE FIELD="/insertRegulatedActivityInput;2;0">
</MAPDELETE>
</MAP>
</INVOKE>
</SEQUENCE>
</LOOP>

<INVOKE TIMEOUT="" SERVICE="ADESPCompliance.maps:saveComplianceReport" VALIDATE-IN="$none" VALIDATE-OUT="$none">
  <COMMENT></COMMENT>

  <!-- nodes -->

<MAP MODE="INPUT">
  <MAPTARGET>

<Values version="2.0">
  <record name="xml" javaclass="com.wm.util.Values">
    <value name="node_type">record</value>
    <value name="node_subtype">unknown</value>
    <value name="is_public">false</value>
    <value name="field_type">record</value>
    <value name="field_dim">0</value>
    <value name="wrapper_type">IData</value>
    <value name="nillable">true</value>
    <value name="form_qualified">false</value>
    <value name="is_global">false</value>
    <array name="rec_fields" type="record" depth="1">
      <record javaclass="com.wm.util.Values">
        <value name="node_type">record</value>
        <value name="node_subtype">unknown</value>
        <value name="node_comment"></value>
        <record name="node_hints" javaclass="com.wm.util.Values">
          <value name="field_largerEditor">false</value>
          <value name="field_password">false</value>
        </record>
        <value name="is_public">false</value>
        <value name="field_name">complianceProgramme</value>
        <value name="field_type">recref</value>
        <value name="field_dim">0</value>
        <value name="wrapper_type">IData</value>
        <value name="nillable">true</value>
        <value name="form_qualified">false</value>
        <value name="is_global">false</value>
        <value name="rec_closed">true</value>
        <value name="modifiable">true</value>
        <value name="rec_ref">ADESPCompliance.documents:ComplianceProgram</value>
      </record>
    </array>
    <value name="modifiable">true</value>
  </record>
</Values>
</MAPTARGET>
  <MAPSOURCE>

<Values version="2.0">
  <record name="xml" javaclass="com.wm.util.Values">
    <value name="node_type">record</value>
    <value name="node_subtype">unknown</value>
    <value name="is_public">false</value>
    <value name="field_type">record</value>
    <value name="field_dim">0</value>
    <value name="nillable">true</value>
    <value name="form_qualified">false</value>
    <value name="is_global">false</value>
    <array name="rec_fields" type="record" depth="1">
      <record javaclass="com.wm.util.Values">
        <value name="node_type">record</value>
        <value name="node_subtype">unknown</value>
        <value name="node_comment"></value>
        <record name="node_hints" javaclass="com.wm.util.Values">
          <value name="field_largerEditor">false</value>
          <value name="field_password">false</value>
        </record>
        <value name="is_public">false</value>
        <value name="field_name">complianceProgram</value>
        <value name="field_type">recref</value>
        <value name="field_dim">0</value>
        <value name="wrapper_type">IData</value>
        <value name="nillable">true</value>
        <value name="form_qualified">false</value>
        <value name="is_global">false</value>
        <value name="rec_closed">true</value>
        <value name="modifiable">true</value>
        <value name="rec_ref">ADESPCompliance.documents:ComplianceProgram</value>
      </record>
      <record javaclass="com.wm.util.Values">
        <value name="node_type">record</value>
        <value name="node_subtype">unknown</value>
        <value name="node_comment"></value>
        <record name="node_hints" javaclass="com.wm.util.Values">
          <value name="field_largerEditor">false</value>
          <value name="field_password">false</value>
        </record>
        <value name="is_public">false</value>
        <value name="field_name">logUserInfo</value>
        <value name="field_type">recref</value>
        <value name="field_dim">0</value>
        <value name="wrapper_type">IData</value>
        <value name="nillable">true</value>
        <value name="form_qualified">false</value>
        <value name="is_global">false</value>
        <value name="rec_closed">true</value>
        <value name="modifiable">true</value>
        <value name="rec_ref">IXLoggingServer.documents:LogUserInformation</value>
      </record>
    </array>
    <value name="modifiable">true</value>
  </record>
</Values>
</MAPSOURCE>

  <!-- nodes -->

<MAPCOPY FROM="/complianceProgram;4;0;ADESPCompliance.documents:ComplianceProgram" TO="/complianceProgramme;4;0;ADESPCompliance.documents:ComplianceProgram">
</MAPCOPY>
</MAP>
</INVOKE>
</FLOW>
